cpylib.cpython-38-darwin.so
cpylib-0.2.0.dist-info/LICENSE
cpylib-0.2.0.dist-info/METADATA
cpylib-0.2.0.dist-info/WHEEL
cpylib-0.2.0.dist-info/top_level.txt
cpylib-0.2.0.dist-info/RECORD
