Metadata-Version: 2.1
Name: cpylib
Version: 0.2.0
Summary: A Python package for executing C code
Home-page: https://github.com/hqmdokkai/cpylib.git
Author: Bobby
Author-email: akirasumeragi699@gmail.com
Classifier: Programming Language :: Python :: 3
Classifier: Programming Language :: C
Classifier: License :: OSI Approved :: Apache Software License
Classifier: Operating System :: OS Independent
Requires-Python: >=3.0
License-File: LICENSE
